tamara_payment/__init__.py
tamara_payment/forms.py
tamara_payment/urls.py
tamara_payment/views.py
tamara_payment/commerce/__init__.py
tamara_payment/commerce/checkout.py
tamara_payment/commerce/data_models.py
tamara_payment/commerce/dummy.py
tamara_payment/extensions/__init__.py
tamara_payment/extensions/tamara.py
tamara_payment/templates/tamara_payment.html
tamara_payment/tests/__init__.py
tamara_payment/tests/mixins.py
tamara_payment/tests/test_service.py
tamara_payment/tests/test_views.py
tamara_payment-1.4.0.dist-info/METADATA
tamara_payment-1.4.0.dist-info/WHEEL
tamara_payment-1.4.0.dist-info/top_level.txt
tamara_payment-1.4.0.dist-info/RECORD
