Metadata-Version: 2.4
Name: tamara_payment
Version: 1.4.0
Summary: A library to provide payment gateway for Tamara Payment
Home-page: https://bitbucket.org/akinonteam/tamara-payment/
Author: Akinon
Author-email: dev@akinon.com
Requires-Dist: Django<4.0,>=2.2.9
Requires-Dist: requests
Requires-Dist: djangorestframework<3.15,>=3.11.0
Requires-Dist: mock==4.0.3
Dynamic: author
Dynamic: author-email
Dynamic: description
Dynamic: description-content-type
Dynamic: home-page
Dynamic: requires-dist
Dynamic: summary
